<PAMDataset>
  <PAMRasterBand band="1">
    <Metadata>
      <MDI key="STATISTICS_APPROXIMATE">YES</MDI>
      <MDI key="STATISTICS_MAXIMUM">255</MDI>
      <MDI key="STATISTICS_MEAN">203.88688435231</MDI>
      <MDI key="STATISTICS_MINIMUM">1</MDI>
      <MDI key="STATISTICS_STDDEV">44.651725671283</MDI>
      <MDI key="STATISTICS_VALID_PERCENT">82.76</MDI>
    </Metadata>
  </PAMRasterBand>
  <PAMRasterBand band="2">
    <Metadata>
      <MDI key="STATISTICS_APPROXIMATE">YES</MDI>
      <MDI key="STATISTICS_MAXIMUM">245</MDI>
      <MDI key="STATISTICS_MEAN">203.38462754188</MDI>
      <MDI key="STATISTICS_MINIMUM">3</MDI>
      <MDI key="STATISTICS_STDDEV">45.25772564395</MDI>
      <MDI key="STATISTICS_VALID_PERCENT">82.87</MDI>
    </Metadata>
  </PAMRasterBand>
  <PAMRasterBand band="3">
    <Metadata>
      <MDI key="STATISTICS_APPROXIMATE">YES</MDI>
      <MDI key="STATISTICS_MAXIMUM">255</MDI>
      <MDI key="STATISTICS_MEAN">204.43198959231</MDI>
      <MDI key="STATISTICS_MINIMUM">1</MDI>
      <MDI key="STATISTICS_STDDEV">40.949308803117</MDI>
      <MDI key="STATISTICS_VALID_PERCENT">82.78</MDI>
    </Metadata>
  </PAMRasterBand>
</PAMDataset>
